pyodr/core.pypy38-pp73-darwin.so
pyodr/__init__.py
pyodr/cli.py
pyodr-0.0.2.dist-info/RECORD
pyodr-0.0.2.dist-info/WHEEL
pyodr-0.0.2.dist-info/entry_points.txt
pyodr-0.0.2.dist-info/top_level.txt
pyodr-0.0.2.dist-info/METADATA
