Metadata-Version: 2.1
Name: pyodr
Version: 0.0.2
Summary: It's Android's first OpenOffice Document Reader for Python!
Author: Andreas Stefl
Author-email: stefl.andreas@gmail.com
Requires-Python: >=3.7
Provides-Extra: dev
Requires-Dist: black; extra == "dev"
Provides-Extra: test
Requires-Dist: pytest>=6.0; extra == "test"
